langchain_cerebras/__init__.py
langchain_cerebras/chat_models.py
langchain_cerebras/py.typed
langchain_cerebras-0.7.0.dist-info/LICENSE
langchain_cerebras-0.7.0.dist-info/METADATA
langchain_cerebras-0.7.0.dist-info/WHEEL
langchain_cerebras-0.7.0.dist-info/RECORD
