Metadata-Version: 2.1
Name: langchain-cerebras
Version: 0.7.0
Summary: An integration package connecting Cerebras and LangChain
Home-page: https://github.com/langchain-ai/langchain-cerebras
License: MIT
Requires-Python: >=3.11,<3.13
Classifier: License :: OSI Approved :: MIT License
Classifier: Programming Language :: Python :: 3
Classifier: Programming Language :: Python :: 3.11
Classifier: Programming Language :: Python :: 3.12
Requires-Dist: langchain-core (>=0.3.29,<2.0.0)
Requires-Dist: langchain-openai (>=0.3.0,<2.0.0)
Project-URL: Repository, https://github.com/langchain-ai/langchain-cerebras
Project-URL: Release Notes, https://github.com/langchain-ai/langchain-cerebras/releases
Project-URL: Source Code, https://github.com/langchain-ai/langchain-cerebras/tree/master/libs/cerebras
